LICENSE
heavywait/cli.py
heavywait/heavywait.py
heavywait/prompts.py
heavywait-0.1.1.dist-info/LICENSE
heavywait-0.1.1.dist-info/METADATA
heavywait-0.1.1.dist-info/WHEEL
heavywait-0.1.1.dist-info/entry_points.txt
heavywait-0.1.1.dist-info/RECORD
